rikiri/__init__.py
rikiri/base.py
rikiri/elements.py
rikiri/render.py
rikiri/walk.py
rikiri/contents/README.md
rikiri/contents/css/reveal.css
rikiri/contents/css/reveal.scss
rikiri/contents/css/print/paper.css
rikiri/contents/css/print/pdf.css
rikiri/contents/css/theme/README.md
rikiri/contents/css/theme/beige.css
rikiri/contents/css/theme/black.css
rikiri/contents/css/theme/blood.css
rikiri/contents/css/theme/league.css
rikiri/contents/css/theme/moon.css
rikiri/contents/css/theme/night.css
rikiri/contents/css/theme/serif.css
rikiri/contents/css/theme/simple.css
rikiri/contents/css/theme/sky.css
rikiri/contents/css/theme/solarized.css
rikiri/contents/css/theme/white.css
rikiri/contents/css/theme/source/beige.scss
rikiri/contents/css/theme/source/black.scss
rikiri/contents/css/theme/source/blood.scss
rikiri/contents/css/theme/source/league.scss
rikiri/contents/css/theme/source/moon.scss
rikiri/contents/css/theme/source/night.scss
rikiri/contents/css/theme/source/serif.scss
rikiri/contents/css/theme/source/simple.scss
rikiri/contents/css/theme/source/sky.scss
rikiri/contents/css/theme/source/solarized.scss
rikiri/contents/css/theme/source/white.scss
rikiri/contents/css/theme/template/mixins.scss
rikiri/contents/css/theme/template/settings.scss
rikiri/contents/css/theme/template/theme.scss
rikiri/contents/js/reveal.js
rikiri/contents/lib/css/zenburn.css
rikiri/contents/lib/font/league-gothic/LICENSE
rikiri/contents/lib/font/league-gothic/league-gothic.css
rikiri/contents/lib/font/league-gothic/league-gothic.eot
rikiri/contents/lib/font/league-gothic/league-gothic.ttf
rikiri/contents/lib/font/league-gothic/league-gothic.woff
rikiri/contents/lib/font/source-sans-pro/LICENSE
rikiri/contents/lib/font/source-sans-pro/source-sans-pro-italic.eot
rikiri/contents/lib/font/source-sans-pro/source-sans-pro-italic.ttf
rikiri/contents/lib/font/source-sans-pro/source-sans-pro-italic.woff
rikiri-0.6.dist-info/DESCRIPTION.rst
rikiri-0.6.dist-info/METADATA
rikiri-0.6.dist-info/RECORD
rikiri-0.6.dist-info/WHEEL
rikiri-0.6.dist-info/metadata.json
rikiri-0.6.dist-info/top_level.txt
