Metadata-Version: 2.0
Name: rikiri
Version: 0.6
Summary: Make github presentations like a boss
Home-page: https://github.com/sourcepirate/rikiri.git
Author: Sourcepirate
Author-email: plasmashadowx@gmail.com
License: MIT License
Requires-Dist: jinja2
Requires-Dist: six
Requires-Dist: yattag
